mongoengine_jsonschema/__init__.py
mongoengine_jsonschema/mixin.py
mongoengine_jsonschema-0.1.3.dist-info/LICENSE
mongoengine_jsonschema-0.1.3.dist-info/METADATA
mongoengine_jsonschema-0.1.3.dist-info/WHEEL
mongoengine_jsonschema-0.1.3.dist-info/top_level.txt
mongoengine_jsonschema-0.1.3.dist-info/RECORD
